trackRetriever/__init__.py
trackRetriever-1.0.1.dist-info/LICENSE
trackRetriever-1.0.1.dist-info/METADATA
trackRetriever-1.0.1.dist-info/WHEEL
trackRetriever-1.0.1.dist-info/top_level.txt
trackRetriever-1.0.1.dist-info/RECORD
