Metadata-Version: 2.1
Name: trackRetriever
Version: 1.0.1
Summary: A package to get the track id's/names of your songs
Home-page: https://github.com/gosulap/trackRetriever
Author: Pradhit Gosula
Author-email: pradhitg@gmail.com
License: UNKNOWN
Platform: UNKNOWN
Classifier: Programming Language :: Python :: 3
Classifier: License :: OSI Approved :: MIT License
Classifier: Operating System :: OS Independent
Requires-Dist: spotipy
